infernet_client/__init__.py
infernet_client/__main__.py
infernet_client/error.py
infernet_client/node.py
infernet_client/py.typed
infernet_client/router.py
infernet_client/types.py
infernet_client/chain/__init__.py
infernet_client/chain/abis.py
infernet_client/chain/rpc.py
infernet_client/chain/subscription.py
infernet_client/chain/token.py
infernet_client/chain/wallet.py
infernet_client/chain/wallet_factory.py
infernet_client/cli/__init__.py
infernet_client/cli/options.py
infernet_client/cli/sample_inputs/sub_params.json
infernet_client-1.4.0.dist-info/METADATA
infernet_client-1.4.0.dist-info/WHEEL
infernet_client-1.4.0.dist-info/entry_points.txt
infernet_client-1.4.0.dist-info/RECORD
