Metadata-Version: 2.3
Name: infernet-client
Version: 1.4.0
Summary: Infernet Node v0.3.0 REST client
Author-email: Stelios Rousoglou <stelios@ritual.net>
Requires-Python: >=3.9
Requires-Dist: aiohttp<4.0.0,>=3.9.2
Requires-Dist: click<9.0.0,>=8.1.7
Requires-Dist: infernet-ml<3.0.0,>=2.0.0.81
Requires-Dist: quart<1.0.0,>=0.19.0
Requires-Dist: web3<7.0.0,>=6.19.0
Provides-Extra: development
Requires-Dist: isort<6.0.0,>=5.13.2; extra == 'development'
Requires-Dist: mypy<2.0.0,>=1.9.0; extra == 'development'
Requires-Dist: pre-commit<4.0.0,>=3.7.0; extra == 'development'
Requires-Dist: pytest-asyncio>=0.21.1; extra == 'development'
Requires-Dist: pytest<9.0.0,>=8.1.1; extra == 'development'
